README.rst
setup.py
supervisor_quick.py
supervisor_quick.egg-info/PKG-INFO
supervisor_quick.egg-info/SOURCES.txt
supervisor_quick.egg-info/dependency_links.txt
supervisor_quick.egg-info/requires.txt
supervisor_quick.egg-info/top_level.txt