Metadata-Version: 1.0
Name: supervisor-quick
Version: 0.1.1
Summary: Bypass supervisor's nasty callbacks stack and make it quick!
Home-page: http://lxyu.github.io/supervisor-quick/
Author: Lx Yu
Author-email: i@lxyu.net
License: MIT
Platform: UNKNOWN
